LICENSE
MANIFEST.in
README.rst
init-radosgw-agent
logrotate.conf
setup.cfg
setup.py
radosgw_agent/__init__.py
radosgw_agent/cli.py
radosgw_agent/client.py
radosgw_agent/constants.py
radosgw_agent/exceptions.py
radosgw_agent/lock.py
radosgw_agent/request.py
radosgw_agent/sync.py
radosgw_agent/worker.py
radosgw_agent.egg-info/PKG-INFO
radosgw_agent.egg-info/SOURCES.txt
radosgw_agent.egg-info/dependency_links.txt
radosgw_agent.egg-info/entry_points.txt
radosgw_agent.egg-info/requires.txt
radosgw_agent.egg-info/top_level.txt
radosgw_agent/data/__init__.py
radosgw_agent/data/buckets.py
radosgw_agent/data/objects.py
radosgw_agent/data/shards.py
radosgw_agent/data/zones.py
radosgw_agent/util/__init__.py
radosgw_agent/util/configuration.py
radosgw_agent/util/decorators.py
radosgw_agent/util/log.py
radosgw_agent/util/network.py
radosgw_agent/util/obj.py
radosgw_agent/util/string.py
scripts/radosgw-agent