Metadata-Version: 1.0
Name: radosgw-agent
Version: 1.2.4
Summary: Synchronize users and data between radosgw clusters
Home-page: https://github.com/ceph/radosgw-agent
Author: Josh Durgin
Author-email: jdurgin@redhat.com
License: MIT
Keywords: radosgw ceph radosgw-agent
Platform: UNKNOWN
